jewei_mcp_nacos/__init__.py
jewei_mcp_nacos/__main__.py
jewei_mcp_nacos/client.py
jewei_mcp_nacos/server.py
jewei_mcp_nacos/clients/__init__.py
jewei_mcp_nacos/clients/base.py
jewei_mcp_nacos/clients/factory.py
jewei_mcp_nacos/clients/v1.py
jewei_mcp_nacos/clients/v2.py
jewei_mcp_nacos/clients/v3.py
jewei_mcp_nacos-0.1.8.dist-info/METADATA
jewei_mcp_nacos-0.1.8.dist-info/WHEEL
jewei_mcp_nacos-0.1.8.dist-info/entry_points.txt
jewei_mcp_nacos-0.1.8.dist-info/licenses/LICENSE
jewei_mcp_nacos-0.1.8.dist-info/RECORD
