Metadata-Version: 2.4
Name: jewei-mcp-nacos
Version: 0.1.8
Summary: MCP Server for Nacos configuration management
Project-URL: Homepage, https://github.com/jeweis/jewei-mcp-nacos
Project-URL: Repository, https://github.com/jeweis/jewei-mcp-nacos
Author: Jeweis
License-Expression: MIT
License-File: LICENSE
Keywords: configuration,mcp,model-context-protocol,nacos
Classifier: Development Status :: 4 - Beta
Classifier: Intended Audience :: Developers
Classifier: License :: OSI Approved :: MIT License
Classifier: Programming Language :: Python :: 3
Classifier: Programming Language :: Python :: 3.10
Classifier: Programming Language :: Python :: 3.11
Classifier: Programming Language :: Python :: 3.12
Requires-Python: >=3.10
Requires-Dist: httpx>=0.27.0
Requires-Dist: mcp>=1.0.0
Requires-Dist: pydantic>=2.0.0
Provides-Extra: dev
Requires-Dist: mypy>=1.10.0; extra == 'dev'
Requires-Dist: pytest-asyncio>=0.23.0; extra == 'dev'
Requires-Dist: pytest>=8.0.0; extra == 'dev'
Requires-Dist: ruff>=0.4.0; extra == 'dev'
